bubbleRL/__init__.py
bubbleRL/bubble_class.py
bubbleRL-1.0.0.dist-info/METADATA
bubbleRL-1.0.0.dist-info/WHEEL
bubbleRL-1.0.0.dist-info/top_level.txt
bubbleRL-1.0.0.dist-info/RECORD
