Metadata-Version: 2.1
Name: bubbleRL
Version: 1.0.0
Summary: Library for all Bubble.io request methods and utilitys
Home-page: https://github.com/israelcetinaa
Author: José Israel Cetina Palomo
Author-email: israel.cetinaa.28@gmail.com
License: MIT
Requires-Dist: requests
